ACedIt/__init__.py
ACedIt/exceptions.py
ACedIt/main.py
ACedIt/util.py
ACedIt-1.0.1.dist-info/DESCRIPTION.rst
ACedIt-1.0.1.dist-info/METADATA
ACedIt-1.0.1.dist-info/RECORD
ACedIt-1.0.1.dist-info/WHEEL
ACedIt-1.0.1.dist-info/entry_points.txt
ACedIt-1.0.1.dist-info/metadata.json
ACedIt-1.0.1.dist-info/top_level.txt
